dagster_celery_k8s/__init__.py
dagster_celery_k8s/app.py
dagster_celery_k8s/config.py
dagster_celery_k8s/executor.py
dagster_celery_k8s/launcher.py
dagster_celery_k8s/version.py
dagster_celery_k8s-1.0.5.dist-info/LICENSE
dagster_celery_k8s-1.0.5.dist-info/METADATA
dagster_celery_k8s-1.0.5.dist-info/WHEEL
dagster_celery_k8s-1.0.5.dist-info/top_level.txt
dagster_celery_k8s-1.0.5.dist-info/RECORD
