Metadata-Version: 2.1
Name: dagster-celery-k8s
Version: 1.0.5
Summary: A Dagster integration for celery-k8s-executor
Home-page: https://github.com/dagster-io/dagster/tree/master/python_modules/libraries/dagster-celery-k8s
Author: Elementl
License: Apache-2.0
Platform: UNKNOWN
Classifier: Programming Language :: Python :: 3.7
Classifier: Programming Language :: Python :: 3.8
Classifier: Programming Language :: Python :: 3.9
Classifier: Programming Language :: Python :: 3.10
Classifier: License :: OSI Approved :: Apache Software License
Classifier: Operating System :: OS Independent
License-File: LICENSE
Requires-Dist: dagster (==1.0.5)
Requires-Dist: dagster-k8s (==1.0.5)
Requires-Dist: dagster-celery (==1.0.5)
